src/__init__.py
src/main.py
fusionx20-0.0.4.dist-info/METADATA
fusionx20-0.0.4.dist-info/WHEEL
fusionx20-0.0.4.dist-info/top_level.txt
fusionx20-0.0.4.dist-info/RECORD
